{
  "$schema": "https://schema.management.azure.com/schemas/2019-04-01/deploymentTemplate.json#",
  "contentVersion": "1.0.0.0",
  "parameters": {
    "sites_redrfid_name": {
      "type": "String"
    },
    "databaseAccounts_red_name": {
      "type": "String"
    },
    "virtualNetworks_REDAppvn_name": {
      "type": "String"
    },
    "serverfarms_ASP_rgREDApp_a1e2_name": {
      "type": "String"
    },
    "vaults_RED_RFID_CapstoneC_name": {
      "type": "String"
    },
    "storageAccounts_redappbulk_name": {
      "type": "String"
    },
    "publicIPAddresses_public_RED_A_name": {
      "type": "String"
    },
    "dnszones_physicalsecurityatlas_com_name": {
      "type": "String"
    },
    "certificates_RED_RFID_CapstoneC_server_name": {
      "type": "String"
    },
    "dnszones_www_physicalsecurityatlas_com_name": {
      "type": "String"
    },
    "ciamDirectories_redrfid_onmicrosoft_com_name": {
      "type": "String"
    }
  },
  "variables": {},
  "resources": [
    {
      "type": "Microsoft.AzureActiveDirectory/ciamDirectories",
      "apiVersion": "2023-05-17-preview",
      "name": "[parameters('ciamDirectories_redrfid_onmicrosoft_com_name')]",
      "location": "United States",
      "sku": {
        "name": "Base",
        "tier": "A0"
      },
      "properties": {
        "createTenantProperties": {
          "displayName": "RED RFID Exploit Database",
          "countryCode": "US"
        },
        "tenantId": "8ea89b1d-21dd-4816-8dda-4a92902bb184"
      }
    },
    {
      "type": "Microsoft.Network/dnszones",
      "apiVersion": "2023-07-01-preview",
      "name": "[parameters('dnszones_physicalsecurityatlas_com_name')]",
      "location": "global",
      "properties": {
        "zoneType": "Public"
      }
    },
    {
      "type": "Microsoft.Network/dnszones",
      "apiVersion": "2023-07-01-preview",
      "name": "[parameters('dnszones_www_physicalsecurityatlas_com_name')]",
      "location": "global",
      "properties": {
        "zoneType": "Public"
      }
    },
    {
      "type": "Microsoft.Network/publicIPAddresses",
      "apiVersion": "2024-07-01",
      "name": "[parameters('publicIPAddresses_public_RED_A_name')]",
      "location": "eastus2",
      "sku": {
        "name": "Standard",
        "tier": "Regional"
      },
      "zones": [
        "1",
        "2",
        "3"
      ],
      "properties": {
        "ipAddress": "68.220.9.20",
        "publicIPAddressVersion": "IPv4",
        "publicIPAllocationMethod": "Static",
        "idleTimeoutInMinutes": 4,
        "ipTags": []
      }
    },
    {
      "type": "Microsoft.Network/virtualNetworks",
      "apiVersion": "2024-07-01",
      "name": "[parameters('virtualNetworks_REDAppvn_name')]",
      "location": "eastus2",
      "properties": {
        "addressSpace": {
          "addressPrefixes": [
            "10.0.0.0/16"
          ]
        },
        "encryption": {
          "enabled": false,
          "enforcement": "AllowUnencrypted"
        },
        "privateEndpointVNetPolicies": "Disabled",
        "subnets": [
          {
            "name": "default",
            "id": "[resourceId('Microsoft.Network/virtualNetworks/subnets', parameters('virtualNetworks_REDAppvn_name'), 'default')]",
            "properties": {
              "addressPrefixes": [
                "10.0.0.0/24"
              ],
              "serviceEndpoints": [
                {
                  "service": "Microsoft.KeyVault",
                  "locations": [
                    "*"
                  ]
                },
                {
                  "service": "Microsoft.AzureCosmosDB",
                  "locations": [
                    "*"
                  ]
                }
              ],
              "delegations": [
                {
                  "name": "delegation",
                  "id": "[concat(resourceId('Microsoft.Network/virtualNetworks/subnets', parameters('virtualNetworks_REDAppvn_name'), 'default'), '/delegations/delegation')]",
                  "properties": {
                    "serviceName": "Microsoft.Web/serverfarms"
                  },
                  "type": "Microsoft.Network/virtualNetworks/subnets/delegations"
                }
              ],
              "privateEndpointNetworkPolicies": "Disabled",
              "privateLinkServiceNetworkPolicies": "Enabled"
            },
            "type": "Microsoft.Network/virtualNetworks/subnets"
          }
        ],
        "virtualNetworkPeerings": [],
        "enableDdosProtection": false
      }
    },
    {
      "type": "Microsoft.Storage/storageAccounts",
      "apiVersion": "2025-01-01",
      "name": "[parameters('storageAccounts_redappbulk_name')]",
      "location": "eastus",
      "sku": {
        "name": "Standard_LRS",
        "tier": "Standard"
      },
      "kind": "StorageV2",
      "properties": {
        "dnsEndpointType": "Standard",
        "allowedCopyScope": "AAD",
        "defaultToOAuthAuthentication": true,
        "publicNetworkAccess": "Enabled",
        "allowCrossTenantReplication": false,
        "minimumTlsVersion": "TLS1_2",
        "allowBlobPublicAccess": false,
        "allowSharedKeyAccess": true,
        "largeFileSharesState": "Enabled",
        "networkAcls": {
          "bypass": "AzureServices",
          "virtualNetworkRules": [],
          "ipRules": [],
          "defaultAction": "Allow"
        },
        "supportsHttpsTrafficOnly": true,
        "encryption": {
          "requireInfrastructureEncryption": true,
          "services": {
            "file": {
              "keyType": "Account",
              "enabled": true
            },
            "table": {
              "keyType": "Account",
              "enabled": true
            },
            "queue": {
              "keyType": "Account",
              "enabled": true
            },
            "blob": {
              "keyType": "Account",
              "enabled": true
            }
          },
          "keySource": "Microsoft.Storage"
        },
        "accessTier": "Hot"
      }
    },
    {
      "type": "Microsoft.Web/serverfarms",
      "apiVersion": "2024-11-01",
      "name": "[parameters('serverfarms_ASP_rgREDApp_a1e2_name')]",
      "location": "East US 2",
      "sku": {
        "name": "B1",
        "tier": "Basic",
        "size": "B1",
        "family": "B",
        "capacity": 1
      },
      "kind": "linux",
      "properties": {
        "perSiteScaling": false,
        "elasticScaleEnabled": false,
        "maximumElasticWorkerCount": 1,
        "isSpot": false,
        "freeOfferExpirationTime": "2025-10-01T19:33:00Z",
        "reserved": true,
        "isXenon": false,
        "hyperV": false,
        "targetWorkerCount": 0,
        "targetWorkerSizeId": 0,
        "zoneRedundant": false,
        "asyncScalingEnabled": false
      }
    },
    {
      "type": "Microsoft.DocumentDB/databaseAccounts",
      "apiVersion": "2025-05-01-preview",
      "name": "[parameters('databaseAccounts_red_name')]",
      "location": "West US 2",
      "dependsOn": [
        "[resourceId('Microsoft.Network/virtualNetworks/subnets', parameters('virtualNetworks_REDAppvn_name'), 'default')]"
      ],
      "tags": {
        "defaultExperience": "Core (SQL)",
        "hidden-workload-type": "Learning",
        "hidden-cosmos-mmspecial": ""
      },
      "kind": "GlobalDocumentDB",
      "identity": {
        "type": "None"
      },
      "properties": {
        "publicNetworkAccess": "Enabled",
        "enableAutomaticFailover": true,
        "enableMultipleWriteLocations": false,
        "isVirtualNetworkFilterEnabled": true,
        "virtualNetworkRules": [
          {
            "id": "[resourceId('Microsoft.Network/virtualNetworks/subnets', parameters('virtualNetworks_REDAppvn_name'), 'default')]",
            "ignoreMissingVNetServiceEndpoint": false
          }
        ],
        "disableKeyBasedMetadataWriteAccess": false,
        "enableFreeTier": true,
        "enableAnalyticalStorage": false,
        "analyticalStorageConfiguration": {
          "schemaType": "WellDefined"
        },
        "databaseAccountOfferType": "Standard",
        "enableMaterializedViews": false,
        "capacityMode": "Provisioned",
        "defaultIdentity": "FirstPartyIdentity",
        "networkAclBypass": "None",
        "disableLocalAuth": false,
        "enablePartitionMerge": false,
        "enablePerRegionPerPartitionAutoscale": true,
        "enableBurstCapacity": false,
        "enablePriorityBasedExecution": false,
        "defaultPriorityLevel": "High",
        "minimalTlsVersion": "Tls12",
        "consistencyPolicy": {
          "defaultConsistencyLevel": "Session",
          "maxIntervalInSeconds": 5,
          "maxStalenessPrefix": 100
        },
        "locations": [
          {
            "locationName": "West US 2",
            "failoverPriority": 0,
            "isZoneRedundant": false
          }
        ],
        "cors": [],
        "capabilities": [],
        "ipRules": [
          {
            "ipAddressOrRange": "0.0.0.0"
          },
          {
            "ipAddressOrRange": "104.171.252.174"
          },
          {
            "ipAddressOrRange": "185.98.168.116"
          },
          {
            "ipAddressOrRange": "185.98.168.8"
          },
          {
            "ipAddressOrRange": "4.210.172.107"
          },
          {
            "ipAddressOrRange": "13.88.56.148"
          },
          {
            "ipAddressOrRange": "13.91.105.215"
          },
          {
            "ipAddressOrRange": "40.91.218.243"
          }
        ],
        "backupPolicy": {
          "type": "Periodic",
          "periodicModeProperties": {
            "backupIntervalInMinutes": 240,
            "backupRetentionIntervalInHours": 8,
            "backupStorageRedundancy": "Geo"
          }
        },
        "networkAclBypassResourceIds": [],
        "diagnosticLogSettings": {
          "enableFullTextQuery": "None"
        },
        "capacity": {
          "totalThroughputLimit": 1000
        }
      }
    },
    {
      "type": "Microsoft.DocumentDB/databaseAccounts/cassandraRoleDefinitions",
      "apiVersion": "2025-05-01-preview",
      "name": "[concat(parameters('databaseAccounts_red_name'), '/00000000-0000-0000-0000-000000000003')]",
      "dependsOn": [
        "[resourceId('Microsoft.DocumentDB/databaseAccounts', parameters('databaseAccounts_red_name'))]"
      ],
      "properties": {
        "roleName": "Cosmos DB Cassandra Built-in Data Reader",
        "type": "BuiltInRole",
        "assignableScopes": [
          "[resourceId('Microsoft.DocumentDB/databaseAccounts', parameters('databaseAccounts_red_name'))]"
        ],
        "permissions": [
          {
            "dataActions": [
              "Microsoft.DocumentDB/databaseAccounts/readMetadata",
              "Microsoft.DocumentDB/databaseAccounts/throughputSettings/read",
              "Microsoft.DocumentDB/databaseAccounts/cassandra/containers/executeQuery",
              "Microsoft.DocumentDB/databaseAccounts/cassandra/containers/readChangeFeed",
              "Microsoft.DocumentDB/databaseAccounts/cassandra/containers/entities/read"
            ],
            "notDataActions": []
          }
        ]
      }
    },
    {
      "type": "Microsoft.DocumentDB/databaseAccounts/cassandraRoleDefinitions",
      "apiVersion": "2025-05-01-preview",
      "name": "[concat(parameters('databaseAccounts_red_name'), '/00000000-0000-0000-0000-000000000004')]",
      "dependsOn": [
        "[resourceId('Microsoft.DocumentDB/databaseAccounts', parameters('databaseAccounts_red_name'))]"
      ],
      "properties": {
        "roleName": "Cosmos DB Cassandra Built-in Data Contributor",
        "type": "BuiltInRole",
        "assignableScopes": [
          "[resourceId('Microsoft.DocumentDB/databaseAccounts', parameters('databaseAccounts_red_name'))]"
        ],
        "permissions": [
          {
            "dataActions": [
              "Microsoft.DocumentDB/databaseAccounts/readMetadata",
              "Microsoft.DocumentDB/databaseAccounts/throughputSettings/read",
              "Microsoft.DocumentDB/databaseAccounts/throughputSettings/write",
              "Microsoft.DocumentDB/databaseAccounts/cassandra/*",
              "Microsoft.DocumentDB/databaseAccounts/cassandra/write",
              "Microsoft.DocumentDB/databaseAccounts/cassandra/delete",
              "Microsoft.DocumentDB/databaseAccounts/cassandra/containers/*",
              "Microsoft.DocumentDB/databaseAccounts/cassandra/containers/entities/*"
            ],
            "notDataActions": []
          }
        ]
      }
    },
    {
      "type": "Microsoft.DocumentDB/databaseAccounts/gremlinRoleDefinitions",
      "apiVersion": "2025-05-01-preview",
      "name": "[concat(parameters('databaseAccounts_red_name'), '/00000000-0000-0000-0000-000000000003')]",
      "dependsOn": [
        "[resourceId('Microsoft.DocumentDB/databaseAccounts', parameters('databaseAccounts_red_name'))]"
      ],
      "properties": {
        "roleName": "Cosmos DB Gremlin Built-in Data Reader",
        "type": "BuiltInRole",
        "assignableScopes": [
          "[resourceId('Microsoft.DocumentDB/databaseAccounts', parameters('databaseAccounts_red_name'))]"
        ],
        "permissions": [
          {
            "dataActions": [
              "Microsoft.DocumentDB/databaseAccounts/readMetadata",
              "Microsoft.DocumentDB/databaseAccounts/throughputSettings/read",
              "Microsoft.DocumentDB/databaseAccounts/gremlin/containers/executeQuery",
              "Microsoft.DocumentDB/databaseAccounts/gremlin/containers/readChangeFeed",
              "Microsoft.DocumentDB/databaseAccounts/gremlin/containers/entities/read"
            ],
            "notDataActions": []
          }
        ]
      }
    },
    {
      "type": "Microsoft.DocumentDB/databaseAccounts/gremlinRoleDefinitions",
      "apiVersion": "2025-05-01-preview",
      "name": "[concat(parameters('databaseAccounts_red_name'), '/00000000-0000-0000-0000-000000000004')]",
      "dependsOn": [
        "[resourceId('Microsoft.DocumentDB/databaseAccounts', parameters('databaseAccounts_red_name'))]"
      ],
      "properties": {
        "roleName": "Cosmos DB Gremlin Built-in Data Contributor",
        "type": "BuiltInRole",
        "assignableScopes": [
          "[resourceId('Microsoft.DocumentDB/databaseAccounts', parameters('databaseAccounts_red_name'))]"
        ],
        "permissions": [
          {
            "dataActions": [
              "Microsoft.DocumentDB/databaseAccounts/readMetadata",
              "Microsoft.DocumentDB/databaseAccounts/throughputSettings/read",
              "Microsoft.DocumentDB/databaseAccounts/throughputSettings/write",
              "Microsoft.DocumentDB/databaseAccounts/gremlin/*",
              "Microsoft.DocumentDB/databaseAccounts/gremlin/write",
              "Microsoft.DocumentDB/databaseAccounts/gremlin/delete",
              "Microsoft.DocumentDB/databaseAccounts/gremlin/containers/*",
              "Microsoft.DocumentDB/databaseAccounts/gremlin/containers/entities/*"
            ],
            "notDataActions": []
          }
        ]
      }
    },
    {
      "type": "Microsoft.DocumentDB/databaseAccounts/mongoMIRoleDefinitions",
      "apiVersion": "2025-05-01-preview",
      "name": "[concat(parameters('databaseAccounts_red_name'), '/00000000-0000-0000-0000-000000000003')]",
      "dependsOn": [
        "[resourceId('Microsoft.DocumentDB/databaseAccounts', parameters('databaseAccounts_red_name'))]"
      ],
      "properties": {
        "roleName": "Cosmos DB Mongo Built-in Data Reader",
        "type": "BuiltInRole",
        "assignableScopes": [
          "[resourceId('Microsoft.DocumentDB/databaseAccounts', parameters('databaseAccounts_red_name'))]"
        ],
        "permissions": [
          {
            "dataActions": [
              "Microsoft.DocumentDB/databaseAccounts/readMetadata",
              "Microsoft.DocumentDB/databaseAccounts/throughputSettings/read",
              "Microsoft.DocumentDB/databaseAccounts/mongoMI/containers/executeQuery",
              "Microsoft.DocumentDB/databaseAccounts/mongoMI/containers/readChangeFeed",
              "Microsoft.DocumentDB/databaseAccounts/mongoMI/containers/entities/read"
            ],
            "notDataActions": []
          }
        ]
      }
    },
    {
      "type": "Microsoft.DocumentDB/databaseAccounts/mongoMIRoleDefinitions",
      "apiVersion": "2025-05-01-preview",
      "name": "[concat(parameters('databaseAccounts_red_name'), '/00000000-0000-0000-0000-000000000004')]",
      "dependsOn": [
        "[resourceId('Microsoft.DocumentDB/databaseAccounts', parameters('databaseAccounts_red_name'))]"
      ],
      "properties": {
        "roleName": "Cosmos DB Mongo Built-in Data Contributor",
        "type": "BuiltInRole",
        "assignableScopes": [
          "[resourceId('Microsoft.DocumentDB/databaseAccounts', parameters('databaseAccounts_red_name'))]"
        ],
        "permissions": [
          {
            "dataActions": [
              "Microsoft.DocumentDB/databaseAccounts/readMetadata",
              "Microsoft.DocumentDB/databaseAccounts/throughputSettings/read",
              "Microsoft.DocumentDB/databaseAccounts/throughputSettings/write",
              "Microsoft.DocumentDB/databaseAccounts/mongoMI/*",
              "Microsoft.DocumentDB/databaseAccounts/mongoMI/write",
              "Microsoft.DocumentDB/databaseAccounts/mongoMI/delete",
              "Microsoft.DocumentDB/databaseAccounts/mongoMI/containers/*",
              "Microsoft.DocumentDB/databaseAccounts/mongoMI/containers/entities/*"
            ],
            "notDataActions": []
          }
        ]
      }
    },
    {
      "type": "Microsoft.DocumentDB/databaseAccounts/sqlDatabases",
      "apiVersion": "2025-05-01-preview",
      "name": "[concat(parameters('databaseAccounts_red_name'), '/', parameters('databaseAccounts_red_name'))]",
      "dependsOn": [
        "[resourceId('Microsoft.DocumentDB/databaseAccounts', parameters('databaseAccounts_red_name'))]"
      ],
      "properties": {
        "resource": {
          "id": "RED"
        }
      }
    },
    {
      "type": "Microsoft.DocumentDB/databaseAccounts/sqlRoleDefinitions",
      "apiVersion": "2025-05-01-preview",
      "name": "[concat(parameters('databaseAccounts_red_name'), '/00000000-0000-0000-0000-000000000001')]",
      "dependsOn": [
        "[resourceId('Microsoft.DocumentDB/databaseAccounts', parameters('databaseAccounts_red_name'))]"
      ],
      "properties": {
        "roleName": "Cosmos DB Built-in Data Reader",
        "type": "BuiltInRole",
        "assignableScopes": [
          "[resourceId('Microsoft.DocumentDB/databaseAccounts', parameters('databaseAccounts_red_name'))]"
        ],
        "permissions": [
          {
            "dataActions": [
              "Microsoft.DocumentDB/databaseAccounts/readMetadata",
              "Microsoft.DocumentDB/databaseAccounts/sqlDatabases/containers/executeQuery",
              "Microsoft.DocumentDB/databaseAccounts/sqlDatabases/containers/readChangeFeed",
              "Microsoft.DocumentDB/databaseAccounts/sqlDatabases/containers/items/read"
            ],
            "notDataActions": []
          }
        ]
      }
    },
    {
      "type": "Microsoft.DocumentDB/databaseAccounts/sqlRoleDefinitions",
      "apiVersion": "2025-05-01-preview",
      "name": "[concat(parameters('databaseAccounts_red_name'), '/00000000-0000-0000-0000-000000000002')]",
      "dependsOn": [
        "[resourceId('Microsoft.DocumentDB/databaseAccounts', parameters('databaseAccounts_red_name'))]"
      ],
      "properties": {
        "roleName": "Cosmos DB Built-in Data Contributor",
        "type": "BuiltInRole",
        "assignableScopes": [
          "[resourceId('Microsoft.DocumentDB/databaseAccounts', parameters('databaseAccounts_red_name'))]"
        ],
        "permissions": [
          {
            "dataActions": [
              "Microsoft.DocumentDB/databaseAccounts/readMetadata",
              "Microsoft.DocumentDB/databaseAccounts/sqlDatabases/containers/*",
              "Microsoft.DocumentDB/databaseAccounts/sqlDatabases/containers/items/*"
            ],
            "notDataActions": []
          }
        ]
      }
    },
    {
      "type": "Microsoft.DocumentDB/databaseAccounts/tableRoleDefinitions",
      "apiVersion": "2025-05-01-preview",
      "name": "[concat(parameters('databaseAccounts_red_name'), '/00000000-0000-0000-0000-000000000001')]",
      "dependsOn": [
        "[resourceId('Microsoft.DocumentDB/databaseAccounts', parameters('databaseAccounts_red_name'))]"
      ],
      "properties": {
        "roleName": "Cosmos DB Built-in Data Reader",
        "type": "BuiltInRole",
        "assignableScopes": [
          "[resourceId('Microsoft.DocumentDB/databaseAccounts', parameters('databaseAccounts_red_name'))]"
        ],
        "permissions": [
          {
            "dataActions": [
              "Microsoft.DocumentDB/databaseAccounts/readMetadata",
              "Microsoft.DocumentDB/databaseAccounts/tables/containers/executeQuery",
              "Microsoft.DocumentDB/databaseAccounts/tables/containers/readChangeFeed",
              "Microsoft.DocumentDB/databaseAccounts/tables/containers/entities/read"
            ],
            "notDataActions": []
          }
        ]
      }
    },
    {
      "type": "Microsoft.DocumentDB/databaseAccounts/tableRoleDefinitions",
      "apiVersion": "2025-05-01-preview",
      "name": "[concat(parameters('databaseAccounts_red_name'), '/00000000-0000-0000-0000-000000000002')]",
      "dependsOn": [
        "[resourceId('Microsoft.DocumentDB/databaseAccounts', parameters('databaseAccounts_red_name'))]"
      ],
      "properties": {
        "roleName": "Cosmos DB Built-in Data Contributor",
        "type": "BuiltInRole",
        "assignableScopes": [
          "[resourceId('Microsoft.DocumentDB/databaseAccounts', parameters('databaseAccounts_red_name'))]"
        ],
        "permissions": [
          {
            "dataActions": [
              "Microsoft.DocumentDB/databaseAccounts/readMetadata",
              "Microsoft.DocumentDB/databaseAccounts/tables/*",
              "Microsoft.DocumentDB/databaseAccounts/tables/containers/*",
              "Microsoft.DocumentDB/databaseAccounts/tables/containers/entities/*"
            ],
            "notDataActions": []
          }
        ]
      }
    },
    {
      "type": "Microsoft.KeyVault/vaults",
      "apiVersion": "2024-12-01-preview",
      "name": "[parameters('vaults_RED_RFID_CapstoneC_name')]",
      "location": "eastus",
      "dependsOn": [
        "[resourceId('Microsoft.Network/virtualNetworks/subnets', parameters('virtualNetworks_REDAppvn_name'), 'default')]"
      ],
      "tags": {
        "exposure": "online public facing apps",
        "connections": "web app connections"
      },
      "properties": {
        "sku": {
          "family": "A",
          "name": "Standard"
        },
        "tenantId": "8ea89b1d-21dd-4816-8dda-4a92902bb184",
        "networkAcls": {
          "bypass": "AzureServices",
          "defaultAction": "Allow",
          "ipRules": [
            {
              "value": "104.171.252.174/32"
            }
          ],
          "virtualNetworkRules": [
            {
              "id": "[resourceId('Microsoft.Network/virtualNetworks/subnets', parameters('virtualNetworks_REDAppvn_name'), 'default')]",
              "ignoreMissingVnetServiceEndpoint": false
            }
          ]
        },
        "accessPolicies": [
          {
            "tenantId": "8ea89b1d-21dd-4816-8dda-4a92902bb184",
            "objectId": "808f7e4a-601a-4a73-915f-0e67197d55b0",
            "permissions": {
              "keys": [
                "Get",
                "List",
                "Update",
                "Create",
                "Import",
                "Delete",
                "Recover",
                "Backup",
                "Restore",
                "GetRotationPolicy",
                "SetRotationPolicy",
                "Rotate"
              ],
              "secrets": [
                "Get",
                "List",
                "Set",
                "Delete",
                "Recover",
                "Backup",
                "Restore"
              ],
              "certificates": [
                "Get",
                "List",
                "Update",
                "Create",
                "Import",
                "Delete",
                "Recover",
                "Backup",
                "Restore",
                "ManageContacts",
                "ManageIssuers",
                "GetIssuers",
                "ListIssuers",
                "SetIssuers",
                "DeleteIssuers"
              ]
            }
          },
          {
            "tenantId": "8ea89b1d-21dd-4816-8dda-4a92902bb184",
            "objectId": "808f7e4a-601a-4a73-915f-0e67197d55b0",
            "applicationId": "713fb5e9-17c5-4ca6-8e81-80f3c3d2e993",
            "permissions": {
              "keys": [
                "Get",
                "List"
              ],
              "secrets": [
                "Get",
                "List"
              ],
              "certificates": [
                "Get",
                "List"
              ]
            }
          },
          {
            "tenantId": "8ea89b1d-21dd-4816-8dda-4a92902bb184",
            "objectId": "d8bda5ac-8770-43c9-b34b-783323286113",
            "permissions": {
              "keys": [
                "Get",
                "List"
              ],
              "secrets": [
                "Get",
                "List"
              ],
              "certificates": [
                "Get",
                "List"
              ]
            }
          },
          {
            "tenantId": "8ea89b1d-21dd-4816-8dda-4a92902bb184",
            "objectId": "d8a77c3a-5f83-43c4-843c-4605be5c46ce",
            "permissions": {
              "certificates": [
                "List",
                "Get"
              ],
              "keys": [
                "Get",
                "List"
              ],
              "secrets": [
                "List",
                "Get"
              ]
            }
          }
        ],
        "enabledForDeployment": false,
        "enabledForDiskEncryption": false,
        "enabledForTemplateDeployment": false,
        "enableSoftDelete": true,
        "softDeleteRetentionInDays": 90,
        "enableRbacAuthorization": false,
        "vaultUri": "https://red-rfid-capstonec.vault.azure.net/",
        "provisioningState": "Succeeded",
        "publicNetworkAccess": "Enabled"
      }
    },
    {
      "type": "Microsoft.KeyVault/vaults/keys",
      "apiVersion": "2024-12-01-preview",
      "name": "[concat(parameters('vaults_RED_RFID_CapstoneC_name'), '/server')]",
      "location": "eastus",
      "dependsOn": [
        "[resourceId('Microsoft.KeyVault/vaults', parameters('vaults_RED_RFID_CapstoneC_name'))]"
      ],
      "properties": {
        "attributes": {
          "enabled": true,
          "nbf": 1756770633,
          "exp": 1789170633
        }
      }
    },
    {
      "type": "Microsoft.KeyVault/vaults/secrets",
      "apiVersion": "2024-12-01-preview",
      "name": "[concat(parameters('vaults_RED_RFID_CapstoneC_name'), '/nonceIV')]",
      "location": "eastus",
      "dependsOn": [
        "[resourceId('Microsoft.KeyVault/vaults', parameters('vaults_RED_RFID_CapstoneC_name'))]"
      ],
      "properties": {
        "contentType": "IV in Hex, must be 12 bytes or 96 bits for AES GCM",
        "attributes": {
          "enabled": true
        }
      }
    },
    {
      "type": "Microsoft.KeyVault/vaults/secrets",
      "apiVersion": "2024-12-01-preview",
      "name": "[concat(parameters('vaults_RED_RFID_CapstoneC_name'), '/nonceKey')]",
      "location": "eastus",
      "dependsOn": [
        "[resourceId('Microsoft.KeyVault/vaults', parameters('vaults_RED_RFID_CapstoneC_name'))]"
      ],
      "properties": {
        "contentType": "256-bit key in hex for use with generating a nonce",
        "attributes": {
          "enabled": true
        }
      }
    },
    {
      "type": "Microsoft.KeyVault/vaults/secrets",
      "apiVersion": "2024-12-01-preview",
      "name": "[concat(parameters('vaults_RED_RFID_CapstoneC_name'), '/redrfid-hphjgve4caapewc4-server-pass')]",
      "location": "eastus",
      "dependsOn": [
        "[resourceId('Microsoft.KeyVault/vaults', parameters('vaults_RED_RFID_CapstoneC_name'))]"
      ],
      "properties": {
        "attributes": {
          "enabled": true
        }
      }
    },
    {
      "type": "Microsoft.KeyVault/vaults/secrets",
      "apiVersion": "2024-12-01-preview",
      "name": "[concat(parameters('vaults_RED_RFID_CapstoneC_name'), '/server')]",
      "location": "eastus",
      "dependsOn": [
        "[resourceId('Microsoft.KeyVault/vaults', parameters('vaults_RED_RFID_CapstoneC_name'))]"
      ],
      "properties": {
        "contentType": "application/x-pkcs12",
        "attributes": {
          "enabled": true,
          "nbf": 1756770633,
          "exp": 1789170633
        }
      }
    },
    {
      "type": "Microsoft.KeyVault/vaults/secrets",
      "apiVersion": "2024-12-01-preview",
      "name": "[concat(parameters('vaults_RED_RFID_CapstoneC_name'), '/server16SEP2025B')]",
      "location": "eastus",
      "dependsOn": [
        "[resourceId('Microsoft.KeyVault/vaults', parameters('vaults_RED_RFID_CapstoneC_name'))]"
      ],
      "properties": {
        "attributes": {
          "enabled": true
        }
      }
    },
    {
      "type": "Microsoft.Network/dnszones/A",
      "apiVersion": "2023-07-01-preview",
      "name": "[concat(parameters('dnszones_www_physicalsecurityatlas_com_name'), '/@')]",
      "dependsOn": [
        "[resourceId('Microsoft.Network/dnszones', parameters('dnszones_www_physicalsecurityatlas_com_name'))]"
      ],
      "properties": {
        "TTL": 600,
        "ARecords": [
          {
            "ipv4Address": "20.119.144.17"
          }
        ],
        "targetResource": {},
        "trafficManagementProfile": {}
      }
    },
    {
      "type": "Microsoft.Network/dnszones/dnssecConfigs",
      "apiVersion": "2023-07-01-preview",
      "name": "[concat(parameters('dnszones_physicalsecurityatlas_com_name'), '/default')]",
      "dependsOn": [
        "[resourceId('Microsoft.Network/dnszones', parameters('dnszones_physicalsecurityatlas_com_name'))]"
      ]
    },
    {
      "type": "Microsoft.Network/dnszones/NS",
      "apiVersion": "2023-07-01-preview",
      "name": "[concat(parameters('dnszones_physicalsecurityatlas_com_name'), '/@')]",
      "dependsOn": [
        "[resourceId('Microsoft.Network/dnszones', parameters('dnszones_physicalsecurityatlas_com_name'))]"
      ],
      "properties": {
        "TTL": 172800,
        "NSRecords": [
          {
            "nsdname": "ns1-03.azure-dns.com."
          },
          {
            "nsdname": "ns2-03.azure-dns.net."
          },
          {
            "nsdname": "ns3-03.azure-dns.org."
          },
          {
            "nsdname": "ns4-03.azure-dns.info."
          }
        ],
        "targetResource": {},
        "trafficManagementProfile": {}
      }
    },
    {
      "type": "Microsoft.Network/dnszones/NS",
      "apiVersion": "2023-07-01-preview",
      "name": "[concat(parameters('dnszones_www_physicalsecurityatlas_com_name'), '/@')]",
      "dependsOn": [
        "[resourceId('Microsoft.Network/dnszones', parameters('dnszones_www_physicalsecurityatlas_com_name'))]"
      ],
      "properties": {
        "TTL": 172800,
        "NSRecords": [
          {
            "nsdname": "ns1-09.azure-dns.com."
          },
          {
            "nsdname": "ns2-09.azure-dns.net."
          },
          {
            "nsdname": "ns3-09.azure-dns.org."
          },
          {
            "nsdname": "ns4-09.azure-dns.info."
          }
        ],
        "targetResource": {},
        "trafficManagementProfile": {}
      }
    },
    {
      "type": "Microsoft.Network/dnszones/NS",
      "apiVersion": "2023-07-01-preview",
      "name": "[concat(parameters('dnszones_physicalsecurityatlas_com_name'), '/www')]",
      "dependsOn": [
        "[resourceId('Microsoft.Network/dnszones', parameters('dnszones_physicalsecurityatlas_com_name'))]"
      ],
      "properties": {
        "TTL": 3600,
        "NSRecords": [
          {
            "nsdname": "ns1-09.azure-dns.com."
          },
          {
            "nsdname": "ns2-09.azure-dns.net."
          },
          {
            "nsdname": "ns3-09.azure-dns.org."
          },
          {
            "nsdname": "ns4-09.azure-dns.info."
          }
        ],
        "targetResource": {},
        "trafficManagementProfile": {}
      }
    },
    {
      "type": "Microsoft.Network/dnszones/SOA",
      "apiVersion": "2023-07-01-preview",
      "name": "[concat(parameters('dnszones_physicalsecurityatlas_com_name'), '/@')]",
      "dependsOn": [
        "[resourceId('Microsoft.Network/dnszones', parameters('dnszones_physicalsecurityatlas_com_name'))]"
      ],
      "properties": {
        "TTL": 3600,
        "SOARecord": {
          "email": "azuredns-hostmaster.microsoft.com",
          "expireTime": 2419200,
          "host": "ns1-03.azure-dns.com.",
          "minimumTTL": 300,
          "refreshTime": 3600,
          "retryTime": 300,
          "serialNumber": 1
        },
        "targetResource": {},
        "trafficManagementProfile": {}
      }
    },
    {
      "type": "Microsoft.Network/dnszones/SOA",
      "apiVersion": "2023-07-01-preview",
      "name": "[concat(parameters('dnszones_www_physicalsecurityatlas_com_name'), '/@')]",
      "dependsOn": [
        "[resourceId('Microsoft.Network/dnszones', parameters('dnszones_www_physicalsecurityatlas_com_name'))]"
      ],
      "properties": {
        "TTL": 3600,
        "SOARecord": {
          "email": "azuredns-hostmaster.microsoft.com",
          "expireTime": 2419200,
          "host": "ns1-09.azure-dns.com.",
          "minimumTTL": 300,
          "refreshTime": 3600,
          "retryTime": 300,
          "serialNumber": 1
        },
        "targetResource": {},
        "trafficManagementProfile": {}
      }
    },
    {
      "type": "Microsoft.Network/dnszones/TXT",
      "apiVersion": "2023-07-01-preview",
      "name": "[concat(parameters('dnszones_www_physicalsecurityatlas_com_name'), '/@')]",
      "dependsOn": [
        "[resourceId('Microsoft.Network/dnszones', parameters('dnszones_www_physicalsecurityatlas_com_name'))]"
      ],
      "properties": {
        "TTL": 600,
        "TXTRecords": [
          {
            "value": [
              "redrfid-hphjgve4caapewc4.eastus2-01.azurewebsites.net"
            ]
          }
        ],
        "targetResource": {},
        "trafficManagementProfile": {}
      }
    },
    {
      "type": "Microsoft.Network/dnszones/TXT",
      "apiVersion": "2023-07-01-preview",
      "name": "[concat(parameters('dnszones_www_physicalsecurityatlas_com_name'), '/asuid')]",
      "dependsOn": [
        "[resourceId('Microsoft.Network/dnszones', parameters('dnszones_www_physicalsecurityatlas_com_name'))]"
      ],
      "properties": {
        "TTL": 3600,
        "TXTRecords": [
          {
            "value": [
              "14D12FA62452331F67987D00EE604836EAF24B4BB6CED22CBFF12260FE22D81B"
            ]
          }
        ],
        "targetResource": {},
        "trafficManagementProfile": {}
      }
    },
    {
      "type": "Microsoft.Network/virtualNetworks/subnets",
      "apiVersion": "2024-07-01",
      "name": "[concat(parameters('virtualNetworks_REDAppvn_name'), '/default')]",
      "dependsOn": [
        "[resourceId('Microsoft.Network/virtualNetworks', parameters('virtualNetworks_REDAppvn_name'))]"
      ],
      "properties": {
        "addressPrefixes": [
          "10.0.0.0/24"
        ],
        "serviceEndpoints": [
          {
            "service": "Microsoft.KeyVault",
            "locations": [
              "*"
            ]
          },
          {
            "service": "Microsoft.AzureCosmosDB",
            "locations": [
              "*"
            ]
          }
        ],
        "delegations": [
          {
            "name": "delegation",
            "id": "[concat(resourceId('Microsoft.Network/virtualNetworks/subnets', parameters('virtualNetworks_REDAppvn_name'), 'default'), '/delegations/delegation')]",
            "properties": {
              "serviceName": "Microsoft.Web/serverfarms"
            },
            "type": "Microsoft.Network/virtualNetworks/subnets/delegations"
          }
        ],
        "privateEndpointNetworkPolicies": "Disabled",
        "privateLinkServiceNetworkPolicies": "Enabled"
      }
    },
    {
      "type": "Microsoft.Storage/storageAccounts/blobServices",
      "apiVersion": "2025-01-01",
      "name": "[concat(parameters('storageAccounts_redappbulk_name'), '/default')]",
      "dependsOn": [
        "[resourceId('Microsoft.Storage/storageAccounts', parameters('storageAccounts_redappbulk_name'))]"
      ],
      "sku": {
        "name": "Standard_LRS",
        "tier": "Standard"
      },
      "properties": {
        "changeFeed": {
          "enabled": true
        },
        "restorePolicy": {
          "enabled": true,
          "days": 6
        },
        "containerDeleteRetentionPolicy": {
          "enabled": true,
          "days": 7
        },
        "cors": {
          "corsRules": []
        },
        "deleteRetentionPolicy": {
          "allowPermanentDelete": false,
          "enabled": true,
          "days": 7
        },
        "isVersioningEnabled": true
      }
    },
    {
      "type": "Microsoft.Storage/storageAccounts/encryptionScopes",
      "apiVersion": "2025-01-01",
      "name": "[concat(parameters('storageAccounts_redappbulk_name'), '/redencryptionscopetest1')]",
      "dependsOn": [
        "[resourceId('Microsoft.Storage/storageAccounts', parameters('storageAccounts_redappbulk_name'))]"
      ],
      "properties": {
        "source": "Microsoft.Storage",
        "state": "Enabled",
        "requireInfrastructureEncryption": true
      }
    },
    {
      "type": "Microsoft.Storage/storageAccounts/fileServices",
      "apiVersion": "2025-01-01",
      "name": "[concat(parameters('storageAccounts_redappbulk_name'), '/default')]",
      "dependsOn": [
        "[resourceId('Microsoft.Storage/storageAccounts', parameters('storageAccounts_redappbulk_name'))]"
      ],
      "sku": {
        "name": "Standard_LRS",
        "tier": "Standard"
      },
      "properties": {
        "protocolSettings": {
          "smb": {}
        },
        "cors": {
          "corsRules": []
        },
        "shareDeleteRetentionPolicy": {
          "enabled": true,
          "days": 7
        }
      }
    },
    {
      "type": "Microsoft.Storage/storageAccounts/queueServices",
      "apiVersion": "2025-01-01",
      "name": "[concat(parameters('storageAccounts_redappbulk_name'), '/default')]",
      "dependsOn": [
        "[resourceId('Microsoft.Storage/storageAccounts', parameters('storageAccounts_redappbulk_name'))]"
      ],
      "properties": {
        "cors": {
          "corsRules": []
        }
      }
    },
    {
      "type": "Microsoft.Storage/storageAccounts/tableServices",
      "apiVersion": "2025-01-01",
      "name": "[concat(parameters('storageAccounts_redappbulk_name'), '/default')]",
      "dependsOn": [
        "[resourceId('Microsoft.Storage/storageAccounts', parameters('storageAccounts_redappbulk_name'))]"
      ],
      "properties": {
        "cors": {
          "corsRules": []
        }
      }
    },
    {
      "type": "Microsoft.Web/certificates",
      "apiVersion": "2024-11-01",
      "name": "[parameters('certificates_RED_RFID_CapstoneC_server_name')]",
      "location": "East US 2",
      "dependsOn": [
        "[resourceId('Microsoft.KeyVault/vaults', parameters('vaults_RED_RFID_CapstoneC_name'))]"
      ],
      "properties": {
        "hostNames": [
          "redrfid-hphjgve4caapewc4.eastus2-01.azurewebsites.net",
          "redrfidacljprotonmail.onmicrosoft.com"
        ],
        "keyVaultId": "[resourceId('Microsoft.KeyVault/vaults', parameters('vaults_RED_RFID_CapstoneC_name'))]",
        "keyVaultSecretName": "server"
      }
    },
    {
      "type": "Microsoft.Web/sites/basicPublishingCredentialsPolicies",
      "apiVersion": "2024-11-01",
      "name": "[concat(parameters('sites_redrfid_name'), '/ftp')]",
      "location": "East US 2",
      "dependsOn": [
        "[resourceId('Microsoft.Web/sites', parameters('sites_redrfid_name'))]"
      ],
      "tags": {
        "exposure": "online public facing apps",
        "connections": "web app connections",
        "tenant": "original workforce non-external tenant"
      },
      "properties": {
        "allow": true
      }
    },
    {
      "type": "Microsoft.Web/sites/basicPublishingCredentialsPolicies",
      "apiVersion": "2024-11-01",
      "name": "[concat(parameters('sites_redrfid_name'), '/scm')]",
      "location": "East US 2",
      "dependsOn": [
        "[resourceId('Microsoft.Web/sites', parameters('sites_redrfid_name'))]"
      ],
      "tags": {
        "exposure": "online public facing apps",
        "connections": "web app connections",
        "tenant": "original workforce non-external tenant"
      },
      "properties": {
        "allow": false
      }
    },
    {
      "type": "Microsoft.Web/sites/config",
      "apiVersion": "2024-11-01",
      "name": "[concat(parameters('sites_redrfid_name'), '/web')]",
      "location": "East US 2",
      "dependsOn": [
        "[resourceId('Microsoft.Web/sites', parameters('sites_redrfid_name'))]"
      ],
      "tags": {
        "exposure": "online public facing apps",
        "connections": "web app connections",
        "tenant": "original workforce non-external tenant"
      },
      "properties": {
        "numberOfWorkers": 1,
        "defaultDocuments": [
          "Default.htm",
          "Default.html",
          "Default.asp",
          "index.htm",
          "index.html",
          "iisstart.htm",
          "default.aspx",
          "index.php",
          "hostingstart.html"
        ],
        "netFrameworkVersion": "v4.0",
        "linuxFxVersion": "DOTNETCORE|9.0",
        "requestTracingEnabled": false,
        "remoteDebuggingEnabled": false,
        "remoteDebuggingVersion": "VS2022",
        "httpLoggingEnabled": true,
        "acrUseManagedIdentityCreds": false,
        "logsDirectorySizeLimit": 35,
        "detailedErrorLoggingEnabled": false,
        "publishingUsername": "$redrfid",
        "scmType": "None",
        "use32BitWorkerProcess": true,
        "webSocketsEnabled": false,
        "alwaysOn": true,
        "appCommandLine": "dotnet REDRFID.dll",
        "managedPipelineMode": "Integrated",
        "virtualApplications": [
          {
            "virtualPath": "/",
            "physicalPath": "site\\wwwroot",
            "preloadEnabled": true
          }
        ],
        "loadBalancing": "LeastRequests",
        "experiments": {
          "rampUpRules": []
        },
        "autoHealEnabled": false,
        "vnetName": "6ac59043-297c-4de1-a6a2-6078a2e4db1d_default",
        "vnetRouteAllEnabled": true,
        "vnetPrivatePortsCount": 0,
        "publicNetworkAccess": "Enabled",
        "cors": {
          "allowedOrigins": [
            "https://redrfid-hphjgve4caapewc4.eastus2-01.azurewebsites.net",
            "https://red.documents.azure.com:443"
          ],
          "supportCredentials": false
        },
        "localMySqlEnabled": false,
        "managedServiceIdentityId": 27149,
        "ipSecurityRestrictions": [
          {
            "ipAddress": "Any",
            "action": "Allow",
            "priority": 2147483647,
            "name": "Allow all",
            "description": "Allow all access"
          }
        ],
        "ipSecurityRestrictionsDefaultAction": "Allow",
        "scmIpSecurityRestrictions": [
          {
            "ipAddress": "Any",
            "action": "Allow",
            "priority": 2147483647,
            "name": "Allow all",
            "description": "Allow all access"
          }
        ],
        "scmIpSecurityRestrictionsDefaultAction": "Allow",
        "scmIpSecurityRestrictionsUseMain": false,
        "http20Enabled": false,
        "minTlsVersion": "1.2",
        "scmMinTlsVersion": "1.2",
        "ftpsState": "FtpsOnly",
        "preWarmedInstanceCount": 0,
        "elasticWebAppScaleLimit": 0,
        "healthCheckPath": "/",
        "functionsRuntimeScaleMonitoringEnabled": false,
        "minimumElasticInstanceCount": 1,
        "azureStorageAccounts": {},
        "http20ProxyFlag": 0
      }
    },
    {
      "type": "Microsoft.Web/sites/deployments",
      "apiVersion": "2024-11-01",
      "name": "[concat(parameters('sites_redrfid_name'), '/02f2333f-b79d-4d2f-8e06-95766461ff2f')]",
      "location": "East US 2",
      "dependsOn": [
        "[resourceId('Microsoft.Web/sites', parameters('sites_redrfid_name'))]"
      ],
      "properties": {
        "status": 4,
        "author_email": "N/A",
        "author": "N/A",
        "deployer": "Push-Deployer",
        "message": "Created via a push deployment",
        "start_time": "2025-09-11T20:56:20.2512901Z",
        "end_time": "2025-09-11T20:56:30.7010335Z",
        "active": false
      }
    },
    {
      "type": "Microsoft.Web/sites/deployments",
      "apiVersion": "2024-11-01",
      "name": "[concat(parameters('sites_redrfid_name'), '/087b815c-2f2c-4c22-bc93-4f947a25bffc')]",
      "location": "East US 2",
      "dependsOn": [
        "[resourceId('Microsoft.Web/sites', parameters('sites_redrfid_name'))]"
      ],
      "properties": {
        "status": 4,
        "author_email": "N/A",
        "author": "N/A",
        "deployer": "Push-Deployer",
        "message": "Created via a push deployment",
        "start_time": "2025-09-03T16:42:40.5771591Z",
        "end_time": "2025-09-03T16:42:49.4845101Z",
        "active": false
      }
    },
    {
      "type": "Microsoft.Web/sites/deployments",
      "apiVersion": "2024-11-01",
      "name": "[concat(parameters('sites_redrfid_name'), '/201ad207-3475-44bd-9229-06eed5133fac')]",
      "location": "East US 2",
      "dependsOn": [
        "[resourceId('Microsoft.Web/sites', parameters('sites_redrfid_name'))]"
      ],
      "properties": {
        "status": 4,
        "author_email": "N/A",
        "author": "N/A",
        "deployer": "Push-Deployer",
        "message": "Created via a push deployment",
        "start_time": "2025-09-09T22:52:55.1387337Z",
        "end_time": "2025-09-09T22:53:04.4086259Z",
        "active": false
      }
    },
    {
      "type": "Microsoft.Web/sites/deployments",
      "apiVersion": "2024-11-01",
      "name": "[concat(parameters('sites_redrfid_name'), '/35dbcd44-8544-4919-b97d-19ed8d589437')]",
      "location": "East US 2",
      "dependsOn": [
        "[resourceId('Microsoft.Web/sites', parameters('sites_redrfid_name'))]"
      ],
      "properties": {
        "status": 4,
        "author_email": "N/A",
        "author": "N/A",
        "deployer": "Push-Deployer",
        "message": "Created via a push deployment",
        "start_time": "2025-09-09T22:45:22.2619241Z",
        "end_time": "2025-09-09T22:45:31.2863192Z",
        "active": false
      }
    },
    {
      "type": "Microsoft.Web/sites/deployments",
      "apiVersion": "2024-11-01",
      "name": "[concat(parameters('sites_redrfid_name'), '/5747289c-d664-4660-9c58-63ece22647ed')]",
      "location": "East US 2",
      "dependsOn": [
        "[resourceId('Microsoft.Web/sites', parameters('sites_redrfid_name'))]"
      ],
      "properties": {
        "status": 4,
        "author_email": "N/A",
        "author": "N/A",
        "deployer": "Push-Deployer",
        "message": "Created via a push deployment",
        "start_time": "2025-09-16T00:09:00.6051742Z",
        "end_time": "2025-09-16T00:09:17.0081926Z",
        "active": true
      }
    },
    {
      "type": "Microsoft.Web/sites/deployments",
      "apiVersion": "2024-11-01",
      "name": "[concat(parameters('sites_redrfid_name'), '/6442c739-d4cf-44f4-8871-07b42128a59b')]",
      "location": "East US 2",
      "dependsOn": [
        "[resourceId('Microsoft.Web/sites', parameters('sites_redrfid_name'))]"
      ],
      "properties": {
        "status": 4,
        "author_email": "N/A",
        "author": "N/A",
        "deployer": "Push-Deployer",
        "message": "Created via a push deployment",
        "start_time": "2025-09-11T22:08:43.4769503Z",
        "end_time": "2025-09-11T22:08:53.7683049Z",
        "active": false
      }
    },
    {
      "type": "Microsoft.Web/sites/deployments",
      "apiVersion": "2024-11-01",
      "name": "[concat(parameters('sites_redrfid_name'), '/92907c80-ee03-4a59-a249-fd6f6918ef86')]",
      "location": "East US 2",
      "dependsOn": [
        "[resourceId('Microsoft.Web/sites', parameters('sites_redrfid_name'))]"
      ],
      "properties": {
        "status": 4,
        "author_email": "N/A",
        "author": "N/A",
        "deployer": "Push-Deployer",
        "message": "Created via a push deployment",
        "start_time": "2025-09-03T16:53:03.4039002Z",
        "end_time": "2025-09-03T16:53:13.078674Z",
        "active": false
      }
    },
    {
      "type": "Microsoft.Web/sites/deployments",
      "apiVersion": "2024-11-01",
      "name": "[concat(parameters('sites_redrfid_name'), '/a041788f-084b-47a2-b2ac-1b8520a88a61')]",
      "location": "East US 2",
      "dependsOn": [
        "[resourceId('Microsoft.Web/sites', parameters('sites_redrfid_name'))]"
      ],
      "properties": {
        "status": 4,
        "author_email": "N/A",
        "author": "N/A",
        "deployer": "Push-Deployer",
        "message": "Created via a push deployment",
        "start_time": "2025-09-09T20:31:50.8359263Z",
        "end_time": "2025-09-09T20:31:55.9768085Z",
        "active": false
      }
    },
    {
      "type": "Microsoft.Web/sites/deployments",
      "apiVersion": "2024-11-01",
      "name": "[concat(parameters('sites_redrfid_name'), '/ae39aeba-57be-44b9-b47a-ed5e1db7a475')]",
      "location": "East US 2",
      "dependsOn": [
        "[resourceId('Microsoft.Web/sites', parameters('sites_redrfid_name'))]"
      ],
      "properties": {
        "status": 4,
        "author_email": "N/A",
        "author": "N/A",
        "deployer": "Push-Deployer",
        "message": "Created via a push deployment",
        "start_time": "2025-09-03T21:30:12.4146069Z",
        "end_time": "2025-09-03T21:30:27.8779125Z",
        "active": false
      }
    },
    {
      "type": "Microsoft.Web/sites/deployments",
      "apiVersion": "2024-11-01",
      "name": "[concat(parameters('sites_redrfid_name'), '/e532601b-4fde-4336-b524-c3b92f55742c')]",
      "location": "East US 2",
      "dependsOn": [
        "[resourceId('Microsoft.Web/sites', parameters('sites_redrfid_name'))]"
      ],
      "properties": {
        "status": 4,
        "author_email": "N/A",
        "author": "N/A",
        "deployer": "Push-Deployer",
        "message": "Created via a push deployment",
        "start_time": "2025-09-12T01:03:27.4096341Z",
        "end_time": "2025-09-12T01:03:39.9863391Z",
        "active": false
      }
    },
    {
      "type": "Microsoft.Web/sites/hostNameBindings",
      "apiVersion": "2024-11-01",
      "name": "[concat(parameters('sites_redrfid_name'), '/', parameters('sites_redrfid_name'), '-hphjgve4caapewc4.eastus2-01.azurewebsites.net')]",
      "location": "East US 2",
      "dependsOn": [
        "[resourceId('Microsoft.Web/sites', parameters('sites_redrfid_name'))]"
      ],
      "properties": {
        "siteName": "redrfid",
        "hostNameType": "Verified"
      }
    },
    {
      "type": "Microsoft.Web/sites/hostNameBindings",
      "apiVersion": "2024-11-01",
      "name": "[concat(parameters('sites_redrfid_name'), '/www.physicalsecurityatlas.com')]",
      "location": "East US 2",
      "dependsOn": [
        "[resourceId('Microsoft.Web/sites', parameters('sites_redrfid_name'))]"
      ],
      "properties": {
        "siteName": "redrfid",
        "hostNameType": "Verified",
        "sslState": "SniEnabled",
        "thumbprint": "720481B108033A9E198C4DCAFAEECE7CEC768F35"
      }
    },
    {
      "type": "Microsoft.DocumentDB/databaseAccounts/sqlDatabases/containers",
      "apiVersion": "2025-05-01-preview",
      "name": "[concat(parameters('databaseAccounts_red_name'), '/', parameters('databaseAccounts_red_name'), '/', parameters('databaseAccounts_red_name'), 'RecordsB')]",
      "dependsOn": [
        "[resourceId('Microsoft.DocumentDB/databaseAccounts/sqlDatabases', parameters('databaseAccounts_red_name'), parameters('databaseAccounts_red_name'))]",
        "[resourceId('Microsoft.DocumentDB/databaseAccounts', parameters('databaseAccounts_red_name'))]"
      ],
      "properties": {
        "resource": {
          "id": "RedRecordsB",
          "indexingPolicy": {
            "indexingMode": "consistent",
            "automatic": true,
            "includedPaths": [
              {
                "path": "/*"
              }
            ],
            "excludedPaths": [
              {
                "path": "/\"_etag\"/?"
              }
            ]
          },
          "partitionKey": {
            "paths": [
              "/_partitionKey"
            ],
            "kind": "MultiHash",
            "version": 2
          },
          "conflictResolutionPolicy": {
            "mode": "LastWriterWins",
            "conflictResolutionPath": "/_ts"
          }
        }
      }
    },
    {
      "type": "Microsoft.Storage/storageAccounts/blobServices/containers",
      "apiVersion": "2025-01-01",
      "name": "[concat(parameters('storageAccounts_redappbulk_name'), '/default/redtestcontainer1')]",
      "dependsOn": [
        "[resourceId('Microsoft.Storage/storageAccounts/blobServices', parameters('storageAccounts_redappbulk_name'), 'default')]",
        "[resourceId('Microsoft.Storage/storageAccounts', parameters('storageAccounts_redappbulk_name'))]"
      ],
      "properties": {
        "immutableStorageWithVersioning": {
          "enabled": false
        },
        "defaultEncryptionScope": "$account-encryption-key",
        "denyEncryptionScopeOverride": false,
        "publicAccess": "None"
      }
    },
    {
      "type": "Microsoft.Web/sites",
      "apiVersion": "2024-11-01",
      "name": "[parameters('sites_redrfid_name')]",
      "location": "East US 2",
      "dependsOn": [
        "[resourceId('Microsoft.Web/serverfarms', parameters('serverfarms_ASP_rgREDApp_a1e2_name'))]",
        "[resourceId('Microsoft.Network/virtualNetworks/subnets', parameters('virtualNetworks_REDAppvn_name'), 'default')]"
      ],
      "tags": {
        "exposure": "online public facing apps",
        "connections": "web app connections",
        "tenant": "original workforce non-external tenant"
      },
      "kind": "app,linux",
      "identity": {
        "type": "SystemAssigned"
      },
      "properties": {
        "enabled": true,
        "hostNameSslStates": [
          {
            "name": "[concat(parameters('sites_redrfid_name'), '-hphjgve4caapewc4.eastus2-01.azurewebsites.net')]",
            "sslState": "Disabled",
            "hostType": "Standard"
          },
          {
            "name": "[concat(parameters('sites_redrfid_name'), '-hphjgve4caapewc4.scm.eastus2-01.azurewebsites.net')]",
            "sslState": "Disabled",
            "hostType": "Repository"
          },
          {
            "name": "www.physicalsecurityatlas.com",
            "sslState": "SniEnabled",
            "thumbprint": "720481B108033A9E198C4DCAFAEECE7CEC768F35",
            "hostType": "Standard"
          }
        ],
        "serverFarmId": "[resourceId('Microsoft.Web/serverfarms', parameters('serverfarms_ASP_rgREDApp_a1e2_name'))]",
        "reserved": true,
        "isXenon": false,
        "hyperV": false,
        "dnsConfiguration": {},
        "outboundVnetRouting": {
          "allTraffic": false,
          "applicationTraffic": true,
          "contentShareTraffic": false,
          "imagePullTraffic": false,
          "backupRestoreTraffic": false
        },
        "siteConfig": {
          "numberOfWorkers": 1,
          "linuxFxVersion": "DOTNETCORE|9.0",
          "acrUseManagedIdentityCreds": false,
          "alwaysOn": true,
          "http20Enabled": false,
          "functionAppScaleLimit": 0,
          "minimumElasticInstanceCount": 1
        },
        "scmSiteAlsoStopped": false,
        "clientAffinityEnabled": false,
        "clientAffinityProxyEnabled": false,
        "clientCertEnabled": false,
        "clientCertMode": "Required",
        "hostNamesDisabled": false,
        "ipMode": "IPv4",
        "customDomainVerificationId": "14D12FA62452331F67987D00EE604836EAF24B4BB6CED22CBFF12260FE22D81B",
        "containerSize": 0,
        "dailyMemoryTimeQuota": 0,
        "httpsOnly": true,
        "endToEndEncryptionEnabled": false,
        "redundancyMode": "None",
        "publicNetworkAccess": "Enabled",
        "storageAccountRequired": false,
        "virtualNetworkSubnetId": "[resourceId('Microsoft.Network/virtualNetworks/subnets', parameters('virtualNetworks_REDAppvn_name'), 'default')]",
        "keyVaultReferenceIdentity": "SystemAssigned",
        "autoGeneratedDomainNameLabelScope": "TenantReuse",
        "sshEnabled": true
      }
    },
    {
      "type": "Microsoft.Web/sites/virtualNetworkConnections",
      "apiVersion": "2024-11-01",
      "name": "[concat(parameters('sites_redrfid_name'), '/6ac59043-297c-4de1-a6a2-6078a2e4db1d_default')]",
      "location": "East US 2",
      "dependsOn": [
        "[resourceId('Microsoft.Web/sites', parameters('sites_redrfid_name'))]",
        "[resourceId('Microsoft.Network/virtualNetworks/subnets', parameters('virtualNetworks_REDAppvn_name'), 'default')]"
      ],
      "properties": {
        "vnetResourceId": "[resourceId('Microsoft.Network/virtualNetworks/subnets', parameters('virtualNetworks_REDAppvn_name'), 'default')]",
        "isSwift": true
      }
    },
    {
      "type": "Microsoft.DocumentDB/databaseAccounts/sqlDatabases/containers/throughputSettings",
      "apiVersion": "2025-05-01-preview",
      "name": "[concat(parameters('databaseAccounts_red_name'), '/', parameters('databaseAccounts_red_name'), '/', parameters('databaseAccounts_red_name'), 'RecordsB/default')]",
      "dependsOn": [
        "[resourceId('Microsoft.DocumentDB/databaseAccounts/sqlDatabases/containers', parameters('databaseAccounts_red_name'), parameters('databaseAccounts_red_name'), concat(parameters('databaseAccounts_red_name'), 'RecordsB'))]",
        "[resourceId('Microsoft.DocumentDB/databaseAccounts/sqlDatabases', parameters('databaseAccounts_red_name'), parameters('databaseAccounts_red_name'))]",
        "[resourceId('Microsoft.DocumentDB/databaseAccounts', parameters('databaseAccounts_red_name'))]"
      ],
      "properties": {
        "resource": {
          "throughput": 400
        }
      }
    }
  ]
}